uart.v
//-----------------------------------------------------
// Design Name : uart 
// File Name   : uart.v
//-----------------------------------------------------
module uart #(
	parameter          freq_hz = 50000000,
	parameter          baud    = 38400
) (
	input              reset,
	input              clk,
	// UART lines
	input              uart_rxd,
	output reg         uart_txd,
	// 
	output reg [7:0]   rx_data,
	output reg         rx_avail,
	output reg         rx_error,
	input              rx_ack,
	output reg         rx_busy,
	input      [7:0]   tx_data,
	input              tx_wr,
	output reg         tx_busy
);

parameter divisor = freq_hz/baud/16;

//-----------------------------------------------------------------
// enable16 generator
//-----------------------------------------------------------------
reg [15:0] enable16_counter;

wire    enable16;
assign  enable16 = (enable16_counter == 0);

always @(posedge clk)
begin
	if (reset) begin
		enable16_counter <= divisor-1;
	end else begin
		enable16_counter <= enable16_counter - 1;
		if (enable16_counter == 0) begin
			enable16_counter <= divisor-1;
		end
	end
end

//-----------------------------------------------------------------
// syncronize uart_rxd
//-----------------------------------------------------------------
reg uart_rxd1;
reg uart_rxd2;

always @(posedge clk)
begin
	uart_rxd1 <= uart_rxd;
	uart_rxd2 <= uart_rxd1;
end

//-----------------------------------------------------------------
// UART RX Logic
//-----------------------------------------------------------------
reg [3:0] rx_count16;
reg [3:0] rx_bitcount;
reg [7:0] rxd_reg;

always @ (posedge clk)
begin
	if (reset) begin
		rx_busy     <= 0;
		rx_count16  <= 0;
		rx_bitcount <= 0;
		rx_avail    <= 0;
		rx_error    <= 0;
	end else begin 
		if (rx_ack) begin
			rx_avail <= 0;
			rx_error <= 0;
		end

		if (enable16) begin
			if (!rx_busy) begin           // look for start bit
				if (!uart_rxd2) begin     //     start bit found
					rx_busy     <= 1;
					rx_count16  <= 7;
					rx_bitcount <= 0;
				end
			end else begin
				rx_count16 <= rx_count16 + 1;

				if (rx_count16 == 0) begin      // sample 
					rx_bitcount <= rx_bitcount + 1;

					if (rx_bitcount == 0) begin          // verify startbit
						if (uart_rxd2) begin
							rx_busy <= 0;
						end
					end else if (rx_bitcount == 9) begin // look for stop bit
						rx_busy <= 0;
						if (uart_rxd2) begin             //   stop bit ok
							rx_data  <= rxd_reg;
							rx_avail <= 1;
							rx_error <= 0;
						end else begin                  //   bas stop bit
							rx_error <= 1;
						end
					end else begin
						rxd_reg <= { uart_rxd2, rxd_reg[7:1] };
					end
				end
			end 
		end
	end
end

//-----------------------------------------------------------------
// UART TX Logic
//-----------------------------------------------------------------
reg [3:0] tx_bitcount;
reg [3:0] tx_count16;
reg [7:0] txd_reg;

always @ (posedge clk)
begin
	if (reset) begin
		tx_busy     <= 0;
		uart_txd    <= 1;
		tx_count16  <= 0;
	end else begin
		if (tx_wr && !tx_busy) begin
			txd_reg     <= tx_data;
			tx_bitcount <= 0;
			tx_count16  <= 0;
			tx_busy     <= 1;
		end 

		if (enable16) begin
			tx_count16  <= tx_count16 + 1;

			if ((tx_count16 == 0) && tx_busy) begin
				tx_bitcount <= tx_bitcount + 1;
				
				if (tx_bitcount == 0) begin
					uart_txd <= 'b0;
				end else if (tx_bitcount ==  9) begin
					uart_txd <= 'b1;
				end else if (tx_bitcount == 10) begin
					tx_bitcount <= 0;
					tx_busy  <= 0;
				end else begin
					uart_txd <= txd_reg[0];
					txd_reg  <= { 1'b0, txd_reg[7:1] };
				end
			end

		end
	end
end


endmodule

FIFO.v
module FIFO(wclk,wr,datin,rclk,rd,datout,full,empy,dato,rst);
// Inputs and Outputs 
	input wclk;
	input wr;
	input [dato_width-1:0] datin;
	input rclk;
	input rd;
	input rst;
	output reg [dato_width-1:0] datout;
	output reg full;
	output reg empy;
	output reg dato;
	
//Parameters

parameter dato_width = 8;
parameter fifo_length = 53;

// Registers	
	reg [dato_width-1:0] f [0:fifo_length-1];
	
	reg orwr;
	
	reg [2:0] cont = 0;
	reg [2:0] contw = 0;
	reg [2:0] contr = 0;
	
	always @(posedge wclk) begin
		if(wr == 1 && (~full)) begin
			f[contw] <= datin;
			contw <= contw + 3'b001;	
			if(contw > (fifo_length - 1)) contw <= 3'b000;
		end
	end
	
	always @(posedge rclk) begin
		if(rd == 1 && (~empy)) begin
			datout <= f[contr];
			f[contr] <= 0;
			contr <= contr + 3'b001;
			if(contr > (fifo_length - 1)) contr <= 3'b000;
		end
	end
	
	always @(posedge orwr) begin
		if(rd == 1 && (~empy)) cont <= cont - 3'b001;
		if(wr == 1 && (~full)) cont <= cont + 3'b001;
	end
	
	always @(*) begin
		orwr = wclk | rclk;
/*		if(rst == 1) begin
			f[0] = 3'b000;
			f[1] = 3'b000;
			f[2] = 3'b000;
			f[3] = 3'b000;
			f[4] = 3'b000;
		end */
		if(cont == 0) begin
			empy = 1;
			dato = 0;
			full = 0;
		end
		if(cont > 0) begin
			empy = 0;
			dato = 1;
			full = 0;
		end
		if(cont == fifo_length) begin
			empy = 0;
			dato = 0;
			full = 1;
		end
	end

endmodule

camera_fifo.v
module camera_fifo(clk, reset, tx, rx, datout, rd, rclk, empy, dato, full);
	input rx;
	input reset;
	output tx;
	input clk;
	input rst;
	
	input rclk;
	input rd;
	input [7:0] datout;
	
	input full;
	input empy;
	input dato;
	
	reg wclk = 0;
	reg wr;
	reg [7:0] datin;
	
	FIFO fifo(
		.wclk(wclk), 
		.wr(wr), 
		.datin(datin), 
		.rclk(rclk), .rd(rd), 
		.datout(datout), 
		.full(full), 
		.empy(empy), 
		.dato(dato), 
		.rst(rst)
	);
	
	reg resetu;
	wire [7:0] rx_data;
	reg [7:0] tx_data;
	reg tx_wr;
	wire rx_avail;
	wire rx_busy;
	wire tx_busy;
	
	
	uart peri(
		.reset(reset),
		.clk(clk),
		// UART lines
		.uart_rxd(rx),
		.uart_txd(tx),
		// 
		.rx_data(rx_data),
		.rx_avail(rx_avail),
		.rx_busy(rx_busy),
		.tx_data(tx_data),
		.tx_wr(tx_wr),
		.tx_busy(tx_busy)
	);
	
	/*always @(negedge rx_busy) begin
		if(rx_avail == 1) begin
			datin <= rx_data;
			wr <= 1;
			wclk <= 1;
		end
	end
	
	always @(posedge rx_busy) begin
		wclk <= 0;
		wr <= 0;
	end*/
	
	always @(posedge clk) begin
		if(rx_avail == 1 && rx_busy == 1) begin
			datin <= rx_data;
			wr <= 1;
			wclk <= 1;
		end else begin
			wclk <= 0;
			wr <= 0;
		end
	end
			
	
endmodule

camera_fifo_TB.v
module camera_fifo_TB; 
reg reset;
reg clk;
reg [7:0] Tx;  //Dato de envio
reg send;
reg rdx;
wire txd;
reg rclk = 0;

camera_fifo  uut(
.clk(clk),
.reset(reset),
.rx(rdx),
.tx(txd),
.rclk(rclk)
);

reg [5:0] cont = 0;
	
initial begin 
	clk <= 0;
	rdx <= 1;
	reset=1;
	#10; reset=0;
	
end
	
always #1 clk <= ~clk;

always begin
	for(cont = 0; cont < 15; cont = cont + 1) begin
		#2700;
		rdx <= ~rdx;
	end
	rclk <= 1;
	#2;
	rclk <= 0;
	#2;
	rclk <= 1;
	#2;
	rclk <= 0;
	#2;
end
	 

initial begin//: TEST_CASE
  $dumpfile("camera_fifo_TB.vcd");
  $dumpvars(-1, uut);
  #80000 $finish;



end

endmodule

simulation/camera_fifo_TB.vcd
$date
	Tue Mar 13 13:55:06 2018
$end
$version
	Icarus Verilog
$end
$timescale
	1s
$end
$scope module camera_fifo_TB $end
$scope module uut $end
$var wire 1 ! clk $end
$var wire 1 " dato $end
$var wire 8 # datout [7:0] $end
$var wire 1 $ empy $end
$var wire 1 % full $end
$var wire 1 & rclk $end
$var wire 1 ' rd $end
$var wire 1 ( reset $end
$var wire 1 ) rst $end
$var wire 1 * rx $end
$var wire 1 + rx_avail $end
$var wire 1 , rx_busy $end
$var wire 8 - rx_data [7:0] $end
$var wire 1 . tx $end
$var wire 1 / tx_busy $end
$var reg 8 0 datin [7:0] $end
$var reg 8 1 tx_data [7:0] $end
$var reg 1 2 tx_wr $end
$var reg 1 3 wclk $end
$var reg 1 4 wr $end
$scope module fifo $end
$var wire 8 5 datin [7:0] $end
$var wire 1 & rclk $end
$var wire 1 ' rd $end
$var wire 1 ) rst $end
$var wire 1 6 wclk $end
$var wire 1 7 wr $end
$var reg 3 8 cont [2:0] $end
$var reg 3 9 contr [2:0] $end
$var reg 3 : contw [2:0] $end
$var reg 1 ; dato $end
$var reg 8 < datout [7:0] $end
$var reg 1 = empy $end
$var reg 1 > full $end
$var reg 1 ? orwr $end
$upscope $end
$scope module peri $end
$var wire 1 ! clk $end
$var wire 1 @ enable16 $end
$var wire 1 ( reset $end
$var wire 1 A rx_ack $end
$var wire 8 B tx_data [7:0] $end
$var wire 1 C tx_wr $end
$var wire 1 * uart_rxd $end
$var reg 16 D enable16_counter [15:0] $end
$var reg 1 E rx_avail $end
$var reg 4 F rx_bitcount [3:0] $end
$var reg 1 G rx_busy $end
$var reg 4 H rx_count16 [3:0] $end
$var reg 8 I rx_data [7:0] $end
$var reg 1 J rx_error $end
$var reg 8 K rxd_reg [7:0] $end
$var reg 4 L tx_bitcount [3:0] $end
$var reg 1 M tx_busy $end
$var reg 4 N tx_count16 [3:0] $end
$var reg 8 O txd_reg [7:0] $end
$var reg 1 P uart_rxd1 $end
$var reg 1 Q uart_rxd2 $end
$var reg 1 R uart_txd $end
$upscope $end
$upscope $end
$upscope $end
$enddefinitions $end
#0
$dumpvars
xR
xQ
xP
bx O
bx N
xM
bx L
bx K
xJ
bx I
bx H
xG
bx F
xE
bx D
xC
bx B
zA
x@
x?
0>
1=
bx <
0;
b0 :
b0 9
b0 8
x7
06
bx 5
x4
03
x2
bx 1
bx 0
x/
x.
bx -
x,
x+
1*
z)
1(
z'
z&
0%
1$
bx #
0"
0!
$end
#1
b11010 D
0@
1P
0J
0E
0+
b0 F
b0 H
0G
0,
b0 N
1R
1.
0M
0/
04
07
1!
#2
0!
#3
1Q
1!
#4
0!
#5
1!
#6
0!
#7
1!
#8
0!
#9
1!
#10
0!
0(
#11
b11001 D
1!
#12
0!
#13
b11000 D
1!
#14
0!
#15
b10111 D
1!
#16
0!
#17
b10110 D
1!
#18
0!
#19
b10101 D
1!
#20
0!
#21
b10100 D
1!
#22
0!
#23
b10011 D
1!
#24
0!
#25
b10010 D
1!
#26
0!
#27
b10001 D
1!
#28
0!
#29
b10000 D
1!
#30
0!
#31
b1111 D
1!
#32
0!
#33
b1110 D
1!
#34
0!
#35
b1101 D
1!
#36
0!
#37
b1100 D
1!
#38
0!
#39
b1011 D
1!
#40
0!
#41
b1010 D
1!
#42
0!
#43
b1001 D
1!
#44
0!
#45
b1000 D
1!
#46
0!
#47
b111 D
1!
#48
0!
#49
b110 D
1!
#50
0!
#51
b101 D
1!
#52
0!
#53
b100 D
1!
#54
0!
#55
b11 D
1!
#56
0!
#57
b10 D
1!
#58
0!
#59
b1 D
1!
#60
0!
#61
b0 D
1@
1!
#62
0!
#63
b1 N
b11010 D
0@
1!
#64
0!
#65
b11001 D
1!
#66
0!
#67
b11000 D
1!
#68
0!
#69
b10111 D
1!
#70
0!
#71
b10110 D
1!
#72
0!
#73
b10101 D
1!
#74
0!
#75
b10100 D
1!
#76
0!
#77
b10011 D
1!
#78
0!
#79
b10010 D
1!
#80
0!
#81
b10001 D
1!
#82
0!
#83
b10000 D
1!
#84
0!
#85
b1111 D
1!
#86
0!
#87
b1110 D
1!
#88
0!
#89
b1101 D
1!
#90
0!
#91
b1100 D
1!
#92
0!
#93
b1011 D
1!
#94
0!
#95
b1010 D
1!
#96
0!
#97
b1001 D
1!
#98
0!
#99
b1000 D
1!
#100
0!
#101
b111 D
1!
#102
0!
#103
b110 D
1!
#104
0!
#105
b101 D
1!
#106
0!
#107
b100 D
1!
#108
0!
#109
b11 D
1!
#110
0!
#111
b10 D
1!
#112
0!
#113
b1 D
1!
#114
0!
#115
b0 D
1@
1!
#116
0!
#117
b11010 D
0@
b10 N
1!
#118
0!
#119
b11001 D
1!
#120
0!
#121
b11000 D
1!
#122
0!
#123
b10111 D
1!
#124
0!
#125
b10110 D
1!
#126
0!
#127
b10101 D
1!
#128
0!
#129
b10100 D
1!
#130
0!
#131
b10011 D
1!
#132
0!
#133
b10010 D
1!
#134
0!
#135
b10001 D
1!
#136
0!
#137
b10000 D
1!
#138
0!
#139
b1111 D
1!
#140
0!
#141
b1110 D
1!
#142
0!
#143
b1101 D
1!
#144
0!
#145
b1100 D
1!
#146
0!
#147
b1011 D
1!
#148
0!
#149
b1010 D
1!
#150
0!
#151
b1001 D
1!
#152
0!
#153
b1000 D
1!
#154
0!
#155
b111 D
1!
#156
0!
#157
b110 D
1!
#158
0!
#159
b101 D
1!
#160
0!
#161
b100 D
1!
#162
0!
#163
b11 D
1!
#164
0!
#165
b10 D
1!
#166
0!
#167
b1 D
1!
#168
0!
#169
b0 D
1@
1!
#170
0!
#171
b11 N
b11010 D
0@
1!
#172
0!
#173
b11001 D
1!
#174
0!
#175
b11000 D
1!
#176
0!
#177
b10111 D
1!
#178
0!
#179
b10110 D
1!
#180
0!
#181
b10101 D
1!
#182
0!
#183
b10100 D
1!
#184
0!
#185
b10011 D
1!
#186
0!
#187
b10010 D
1!
#188
0!
#189
b10001 D
1!
#190
0!
#191
b10000 D
1!
#192
0!
#193
b1111 D
1!
#194
0!
#195
b1110 D
1!
#196
0!
#197
b1101 D
1!
#198
0!
#199
b1100 D
1!
#200
0!
#201
b1011 D
1!
#202
0!
#203
b1010 D
1!
#204
0!
#205
b1001 D
1!
#206
0!
#207
b1000 D
1!
#208
0!
#209
b111 D
1!
#210
0!
#211
b110 D
1!
#212
0!
#213
b101 D
1!
#214
0!
#215
b100 D
1!
#216
0!
#217
b11 D
1!
#218
0!
#219
b10 D
1!
#220
0!
#221
b1 D
1!
#222
0!
#223
b0 D
1@
1!
#224
0!
#225
b11010 D
0@
b100 N
1!
#226
0!
#227
b11001 D
1!
#228
0!
#229
b11000 D
1!
#230
0!
#231
b10111 D
1!
#232
0!
#233
b10110 D
1!
#234
0!
#235
b10101 D
1!
#236
0!
#237
b10100 D
1!
#238
0!
#239
b10011 D
1!
#240
0!
#241
b10010 D
1!
#242
0!
#243
b10001 D
1!
#244
0!
#245
b10000 D
1!
#246
0!
#247
b1111 D
1!
#248
0!
#249
b1110 D
1!
#250
0!
#251
b1101 D
1!
#252
0!
#253
b1100 D
1!
#254
0!
#255
b1011 D
1!
#256
0!
#257
b1010 D
1!
#258
0!
#259
b1001 D
1!
#260
0!
#261
b1000 D
1!
#262
0!
#263
b111 D
1!
#264
0!
#265
b110 D
1!
#266
0!
#267
b101 D
1!
#268
0!
#269
b100 D
1!
#270
0!
#271
b11 D
1!
#272
0!
#273
b10 D
1!
#274
0!
#275
b1 D
1!
#276
0!
#277
b0 D
1@
1!
#278
0!
#279
b101 N
b11010 D
0@
1!
#280
0!
#281
b11001 D
1!
#282
0!
#283
b11000 D
1!
#284
0!
#285
b10111 D
1!
#286
0!
#287
b10110 D
1!
#288
0!
#289
b10101 D
1!
#290
0!
#291
b10100 D
1!
#292
0!
#293
b10011 D
1!
#294
0!
#295
b10010 D
1!
#296
0!
#297
b10001 D
1!
#298
0!
#299
b10000 D
1!
#300
0!
#301
b1111 D
1!
#302
0!
#303
b1110 D
1!
#304
0!
#305
b1101 D
1!
#306
0!
#307
b1100 D
1!
#308
0!
#309
b1011 D
1!
#310
0!
#311
b1010 D
1!
#312
0!
#313
b1001 D
1!
#314
0!
#315
b1000 D
1!
#316
0!
#317
b111 D
1!
#318
0!
#319
b110 D
1!
#320
0!
#321
b101 D
1!
#322
0!
#323
b100 D
1!
#324
0!
#325
b11 D
1!
#326
0!
#327
b10 D
1!
#328
0!
#329
b1 D
1!
#330
0!
#331
b0 D
1@
1!
#332
0!
#333
b11010 D
0@
b110 N
1!
#334
0!
#335
b11001 D
1!
#336
0!
#337
b11000 D
1!
#338
0!
#339
b10111 D
1!
#340
0!
#341
b10110 D
1!
#342
0!
#343
b10101 D
1!
#344
0!
#345
b10100 D
1!
#346
0!
#347
b10011 D
1!
#348
0!
#349
b10010 D
1!
#350
0!
#351
b10001 D
1!
#352
0!
#353
b10000 D
1!
#354
0!
#355
b1111 D
1!
#356
0!
#357
b1110 D
1!
#358
0!
#359
b1101 D
1!
#360
0!
#361
b1100 D
1!
#362
0!
#363
b1011 D
1!
#364
0!
#365
b1010 D
1!
#366
0!
#367
b1001 D
1!
#368
0!
#369
b1000 D
1!
#370
0!
#371
b111 D
1!
#372
0!
#373
b110 D
1!
#374
0!
#375
b101 D
1!
#376
0!
#377
b100 D
1!
#378
0!
#379
b11 D
1!
#380
0!
#381
b10 D
1!
#382
0!
#383
b1 D
1!
#384
0!
#385
b0 D
1@
1!
#386
0!
#387
b111 N
b11010 D
0@
1!
#388
0!
#389
b11001 D
1!
#390
0!
#391
b11000 D
1!
#392
0!
#393
b10111 D
1!
#394
0!
#395
b10110 D
1!
#396
0!
#397
b10101 D
1!
#398
0!
#399
b10100 D
1!
#400
0!
#401
b10011 D
1!
#402
0!
#403
b10010 D
1!
#404
0!
#405
b10001 D
1!
#406
0!
#407
b10000 D
1!
#408
0!
#409
b1111 D
1!
#410
0!
#411
b1110 D
1!
#412
0!
#413
b1101 D
1!
#414
0!
#415
b1100 D
1!
#416
0!
#417
b1011 D
1!
#418
0!
#419
b1010 D
1!
#420
0!
#421
b1001 D
1!
#422
0!
#423
b1000 D
1!
#424
0!
#425
b111 D
1!
#426
0!
#427
b110 D
1!
#428
0!
#429
b101 D
1!
#430
0!
#431
b100 D
1!
#432
0!
#433
b11 D
1!
#434
0!
#435
b10 D
1!
#436
0!
#437
b1 D
1!
#438
0!
#439
b0 D
1@
1!
#440
0!
#441
b11010 D
0@
b1000 N
1!
#442
0!
#443
b11001 D
1!
#444
0!
#445
b11000 D
1!
#446
0!
#447
b10111 D
1!
#448
0!
#449
b10110 D
1!
#450
0!
#451
b10101 D
1!
#452
0!
#453
b10100 D
1!
#454
0!
#455
b10011 D
1!
#456
0!
#457
b10010 D
1!
#458
0!
#459
b10001 D
1!
#460
0!
#461
b10000 D
1!
#462
0!
#463
b1111 D
1!
#464
0!
#465
b1110 D
1!
#466
0!
#467
b1101 D
1!
#468
0!
#469
b1100 D
1!
#470
0!
#471
b1011 D
1!
#472
0!
#473
b1010 D
1!
#474
0!
#475
b1001 D
1!
#476
0!
#477
b1000 D
1!
#478
0!
#479
b111 D
1!
#480
0!
#481
b110 D
1!
#482
0!
#483
b101 D
1!
#484
0!
#485
b100 D
1!
#486
0!
#487
b11 D
1!
#488
0!
#489
b10 D
1!
#490
0!
#491
b1 D
1!
#492
0!
#493
b0 D
1@
1!
#494
0!
#495
b1001 N
b11010 D
0@
1!
#496
0!
#497
b11001 D
1!
#498
0!
#499
b11000 D
1!
#500
0!
#501
b10111 D
1!
#502
0!
#503
b10110 D
1!
#504
0!
#505
b10101 D
1!
#506
0!
#507
b10100 D
1!
#508
0!
#509
b10011 D
1!
#510
0!
#511
b10010 D
1!
#512
0!
#513
b10001 D
1!
#514
0!
#515
b10000 D
1!
#516
0!
#517
b1111 D
1!
#518
0!
#519
b1110 D
1!
#520
0!
#521
b1101 D
1!
#522
0!
#523
b1100 D
1!
#524
0!
#525
b1011 D
1!
#526
0!
#527
b1010 D
1!
#528
0!
#529
b1001 D
1!
#530
0!
#531
b1000 D
1!
#532
0!
#533
b111 D
1!
#534
0!
#535
b110 D
1!
#536
0!
#537
b101 D
1!
#538
0!
#539
b100 D
1!
#540
0!
#541
b11 D
1!
#542
0!
#543
b10 D
1!
#544
0!
#545
b1 D
1!
#546
0!
#547
b0 D
1@
1!
#548
0!
#549
b11010 D
0@
b1010 N
1!
#550
0!
#551
b11001 D
1!
#552
0!
#553
b11000 D
1!
#554
0!
#555
b10111 D
1!
#556
0!
#557
b10110 D
1!
#558
0!
#559
b10101 D
1!
#560
0!
#561
b10100 D
1!
#562
0!
#563
b10011 D
1!
#564
0!
#565
b10010 D
1!
#566
0!
#567
b10001 D
1!
#568
0!
#569
b10000 D
1!
#570
0!
#571
b1111 D
1!
#572
0!
#573
b1110 D
1!
#574
0!
#575
b1101 D
1!
#576
0!
#577
b1100 D
1!
#578
0!
#579
b1011 D
1!
#580
0!
#581
b1010 D
1!
#582
0!
#583
b1001 D
1!
#584
0!
#585
b1000 D
1!
#586
0!
#587
b111 D
1!
#588
0!
#589
b110 D
1!
#590
0!
#591
b101 D
1!
#592
0!
#593
b100 D
1!
#594
0!
#595
b11 D
1!
#596
0!
#597
b10 D
1!
#598
0!
#599
b1 D
1!
#600
0!
#601
b0 D
1@
1!
#602
0!
#603
b1011 N
b11010 D
0@
1!
#604
0!
#605
b11001 D
1!
#606
0!
#607
b11000 D
1!
#608
0!
#609
b10111 D
1!
#610
0!
#611
b10110 D
1!
#612
0!
#613
b10101 D
1!
#614
0!
#615
b10100 D
1!
#616
0!
#617
b10011 D
1!
#618
0!
#619
b10010 D
1!
#620
0!
#621
b10001 D
1!
#622
0!
#623
b10000 D
1!
#624
0!
#625
b1111 D
1!
#626
0!
#627
b1110 D
1!
#628
0!
#629
b1101 D
1!
#630
0!
#631
b1100 D
1!
#632
0!
#633
b1011 D
1!
#634
0!
#635
b1010 D
1!
#636
0!
#637
b1001 D
1!
#638
0!
#639
b1000 D
1!
#640
0!
#641
b111 D
1!
#642
0!
#643
b110 D
1!
#644
0!
#645
b101 D
1!
#646
0!
#647
b100 D
1!
#648
0!
#649
b11 D
1!
#650
0!
#651
b10 D
1!
#652
0!
#653
b1 D
1!
#654
0!
#655
b0 D
1@
1!
#656
0!
#657
b11010 D
0@
b1100 N
1!
#658
0!
#659
b11001 D
1!
#660
0!
#661
b11000 D
1!
#662
0!
#663
b10111 D
1!
#664
0!
#665
b10110 D
1!
#666
0!
#667
b10101 D
1!
#668
0!
#669
b10100 D
1!
#670
0!
#671
b10011 D
1!
#672
0!
#673
b10010 D
1!
#674
0!
#675
b10001 D
1!
#676
0!
#677
b10000 D
1!
#678
0!
#679
b1111 D
1!
#680
0!
#681
b1110 D
1!
#682
0!
#683
b1101 D
1!
#684
0!
#685
b1100 D
1!
#686
0!
#687
b1011 D
1!
#688
0!
#689
b1010 D
1!
#690
0!
#691
b1001 D
1!
#692
0!
#693
b1000 D
1!
#694
0!
#695
b111 D
1!
#696
0!
#697
b110 D
1!
#698
0!
#699
b101 D
1!
#700
0!
#701
b100 D
1!
#702
0!
#703
b11 D
1!
#704
0!
#705
b10 D
1!
#706
0!
#707
b1 D
1!
#708
0!
#709
b0 D
1@
1!
#710
0!
#711
b1101 N
b11010 D
0@
1!
#712
0!
#713
b11001 D
1!
#714
0!
#715
b11000 D
1!
#716
0!
#717
b10111 D
1!
#718
0!
#719
b10110 D
1!
#720
0!
#721
b10101 D
1!
#722
0!
#723
b10100 D
1!
#724
0!
#725
b10011 D
1!
#726
0!
#727
b10010 D
1!
#728
0!
#729
b10001 D
1!
#730
0!
#731
b10000 D
1!
#732
0!
#733
b1111 D
1!
#734
0!
#735
b1110 D
1!
#736
0!
#737
b1101 D
1!
#738
0!
#739
b1100 D
1!
#740
0!
#741
b1011 D
1!
#742
0!
#743
b1010 D
1!
#744
0!
#745
b1001 D
1!
#746
0!
#747
b1000 D
1!
#748
0!
#749
b111 D
1!
#750
0!
#751
b110 D
1!
#752
0!
#753
b101 D
1!
#754
0!
#755
b100 D
1!
#756
0!
#757
b11 D
1!
#758
0!
#759
b10 D
1!
#760
0!
#761
b1 D
1!
#762
0!
#763
b0 D
1@
1!
#764
0!
#765
b11010 D
0@
b1110 N
1!
#766
0!
#767
b11001 D
1!
#768
0!
#769
b11000 D
1!
#770
0!
#771
b10111 D
1!
#772
0!
#773
b10110 D
1!
#774
0!
#775
b10101 D
1!
#776
0!
#777
b10100 D
1!
#778
0!
#779
b10011 D
1!
#780
0!
#781
b10010 D
1!
#782
0!
#783
b10001 D
1!
#784
0!
#785
b10000 D
1!
#786
0!
#787
b1111 D
1!
#788
0!
#789
b1110 D
1!
#790
0!
#791
b1101 D
1!
#792
0!
#793
b1100 D
1!
#794
0!
#795
b1011 D
1!
#796
0!
#797
b1010 D
1!
#798
0!
#799
b1001 D
1!
#800
0!
#801
b1000 D
1!
#802
0!
#803
b111 D
1!
#804
0!
#805
b110 D
1!
#806
0!
#807
b101 D
1!
#808
0!
#809
b100 D
1!
#810
0!
#811
b11 D
1!
#812
0!
#813
b10 D
1!
#814
0!
#815
b1 D
1!
#816
0!
#817
b0 D
1@
1!
#818
0!
#819
b1111 N
b11010 D
0@
1!
#820
0!
#821
b11001 D
1!
#822
0!
#823
b11000 D
1!
#824
0!
#825
b10111 D
1!
#826
0!
#827
b10110 D
1!
#828
0!
#829
b10101 D
1!
#830
0!
#831
b10100 D
1!
#832
0!
#833
b10011 D
1!
#834
0!
#835
b10010 D
1!
#836
0!
#837
b10001 D
1!
#838
0!
#839
b10000 D
1!
#840
0!
#841
b1111 D
1!
#842
0!
#843
b1110 D
1!
#844
0!
#845
b1101 D
1!
#846
0!
#847
b1100 D
1!
#848
0!
#849
b1011 D
1!
#850
0!
#851
b1010 D
1!
#852
0!
#853
b1001 D
1!
#854
0!
#855
b1000 D
1!
#856
0!
#857
b111 D
1!
#858
0!
#859
b110 D
1!
#860
0!
#861
b101 D
1!
#862
0!
#863
b100 D
1!
#864
0!
0*
#865
b11 D
0P
1!
#866
0!
#867
0Q
b10 D
1!
#868
0!
#869
b1 D
1!
#870
0!
#871
b0 D
1@
1!
#872
0!
#873
b11010 D
0@
b111 H
1G
1,
b0 N
1!
#874
0!
#875
b11001 D
1!
#876
0!
#877
b11000 D
1!
#878
0!
#879
b10111 D
1!
#880
0!
#881
b10110 D
1!
#882
0!
#883
b10101 D
1!
#884
0!
#885
b10100 D
1!
#886
0!
#887
b10011 D
1!
#888
0!
#889
b10010 D
1!
#890
0!
#891
b10001 D
1!
#892
0!
#893
b10000 D
1!
#894
0!
#895
b1111 D
1!
#896
0!
#897
b1110 D
1!
#898
0!
#899
b1101 D
1!
#900
0!
#901
b1100 D
1!
#902
0!
#903
b1011 D
1!
#904
0!
#905
b1010 D
1!
#906
0!
#907
b1001 D
1!
#908
0!
#909
b1000 D
1!
#910
0!
#911
b111 D
1!
#912
0!
#913
b110 D
1!
#914
0!
#915
b101 D
1!
#916
0!
#917
b100 D
1!
#918
0!
#919
b11 D
1!
#920
0!
#921
b10 D
1!
#922
0!
#923
b1 D
1!
#924
0!
#925
b0 D
1@
1!
#926
0!
#927
b1 N
b1000 H
b11010 D
0@
1!
#928
0!
#929
b11001 D
1!
#930
0!
#931
b11000 D
1!
#932
0!
#933
b10111 D
1!
#934
0!
#935
b10110 D
1!
#936
0!
#937
b10101 D
1!
#938
0!
#939
b10100 D
1!
#940
0!
#941
b10011 D
1!
#942
0!
#943
b10010 D
1!
#944
0!
#945
b10001 D
1!
#946
0!
#947
b10000 D
1!
#948
0!
#949
b1111 D
1!
#950
0!
#951
b1110 D
1!
#952
0!
#953
b1101 D
1!
#954
0!
#955
b1100 D
1!
#956
0!
#957
b1011 D
1!
#958
0!
#959
b1010 D
1!
#960
0!
#961
b1001 D
1!
#962
0!
#963
b1000 D
1!
#964
0!
#965
b111 D
1!
#966
0!
#967
b110 D
1!
#968
0!
#969
b101 D
1!
#970
0!
#971
b100 D
1!
#972
0!
#973
b11 D
1!
#974
0!
#975
b10 D
1!
#976
0!
#977
b1 D
1!
#978
0!
#979
b0 D
1@
1!
#980
0!
#981
b11010 D
0@
b1001 H
b10 N
1!
#982
0!
#983
b11001 D
1!
#984
0!
#985
b11000 D
1!
#986
0!
#987
b10111 D
1!
#988
0!
#989
b10110 D
1!
#990
0!
#991
b10101 D
1!
#992
0!
#993
b10100 D
1!
#994
0!
#995
b10011 D
1!
#996
0!
#997
b10010 D
1!
#998
0!
#999
b10001 D
1!
#1000
0!
#1001
b10000 D
1!
#1002
0!
#1003
b1111 D
1!
#1004
0!
#1005
b1110 D
1!
#1006
0!
#1007
b1101 D
1!
#1008
0!
#1009
b1100 D
1!
#1010
0!
#1011
b1011 D
1!
#1012
0!
#1013
b1010 D
1!
#1014
0!
#1015
b1001 D
1!
#1016
0!
#1017
b1000 D
1!
#1018
0!
#1019
b111 D
1!
#1020
0!
#1021
b110 D
1!
#1022
0!
#1023
b101 D
1!
#1024
0!
#1025
b100 D
1!
#1026
0!
#1027
b11 D
1!
#1028
0!
#1029
b10 D
1!
#1030
0!
#1031
b1 D
1!
#1032
0!
#1033
b0 D
1@
1!
#1034
0!
#1035
b11 N
b1010 H
b11010 D
0@
1!
#1036
0!
#1037
b11001 D
1!
#1038
0!
#1039
b11000 D
1!
#1040
0!
#1041
b10111 D
1!
#1042
0!
#1043
b10110 D
1!
#1044
0!
#1045
b10101 D
1!
#1046
0!
#1047
b10100 D
1!
#1048
0!
#1049
b10011 D
1!
#1050
0!
#1051
b10010 D
1!
#1052
0!
#1053
b10001 D
1!
#1054
0!
#1055
b10000 D
1!
#1056
0!
#1057
b1111 D
1!
#1058
0!
#1059
b1110 D
1!
#1060
0!
#1061
b1101 D
1!
#1062
0!
#1063
b1100 D
1!
#1064
0!
#1065
b1011 D
1!
#1066
0!
#1067
b1010 D
1!
#1068
0!
#1069
b1001 D
1!
#1070
0!
#1071
b1000 D
1!
#1072
0!
#1073
b111 D
1!
#1074
0!
#1075
b110 D
1!
#1076
0!
#1077
b101 D
1!
#1078
0!
#1079
b100 D
1!
#1080
0!
#1081
b11 D
1!
#1082
0!
#1083
b10 D
1!
#1084
0!
#1085
b1 D
1!
#1086
0!
#1087
b0 D
1@
1!
#1088
0!
#1089
b11010 D
0@
b1011 H
b100 N
1!
#1090
0!
#1091
b11001 D
1!
#1092
0!
#1093
b11000 D
1!
#1094
0!
#1095
b10111 D
1!
#1096
0!
#1097
b10110 D
1!
#1098
0!
#1099
b10101 D
1!
#1100
0!
