uart.v
//-----------------------------------------------------
// Design Name : uart 
// File Name   : uart.v
//-----------------------------------------------------
module uart #(
	parameter          freq_hz = 50000000,
	parameter          baud    = 38400
) (
	input              reset,
	input              clk,
	// UART lines
	input              uart_rxd,
	output reg         uart_txd,
	// 
	output reg [7:0]   rx_data,
	output reg         rx_avail,
	output reg         rx_error,
	input              rx_ack,
	output reg         rx_busy,
	input      [7:0]   tx_data,
	input              tx_wr,
	output reg         tx_busy
);

parameter divisor = freq_hz/baud/16;

//-----------------------------------------------------------------
// enable16 generator
//-----------------------------------------------------------------
reg [15:0] enable16_counter;

wire    enable16;
assign  enable16 = (enable16_counter == 0);

always @(posedge clk)
begin
	if (reset) begin
		enable16_counter <= divisor-1;
	end else begin
		enable16_counter <= enable16_counter - 1;
		if (enable16_counter == 0) begin
			enable16_counter <= divisor-1;
		end
	end
end

//-----------------------------------------------------------------
// syncronize uart_rxd
//-----------------------------------------------------------------
reg uart_rxd1;
reg uart_rxd2;

always @(posedge clk)
begin
	uart_rxd1 <= uart_rxd;
	uart_rxd2 <= uart_rxd1;
end

//-----------------------------------------------------------------
// UART RX Logic
//-----------------------------------------------------------------
reg [3:0] rx_count16;
reg [3:0] rx_bitcount;
reg [7:0] rxd_reg;

always @ (posedge clk)
begin
	if (reset) begin
		rx_busy     <= 0;
		rx_count16  <= 0;
		rx_bitcount <= 0;
		rx_avail    <= 0;
		rx_error    <= 0;
	end else begin 
		if (rx_ack) begin
			rx_avail <= 0;
			rx_error <= 0;
		end

		if (enable16) begin
			if (!rx_busy) begin           // look for start bit
				if (!uart_rxd2) begin     //     start bit found
					rx_busy     <= 1;
					rx_count16  <= 7;
					rx_bitcount <= 0;
				end
			end else begin
				rx_count16 <= rx_count16 + 1;

				if (rx_count16 == 0) begin      // sample 
					rx_bitcount <= rx_bitcount + 1;

					if (rx_bitcount == 0) begin          // verify startbit
						if (uart_rxd2) begin
							rx_busy <= 0;
						end
					end else if (rx_bitcount == 9) begin // look for stop bit
						rx_busy <= 0;
						if (uart_rxd2) begin             //   stop bit ok
							rx_data  <= rxd_reg;
							rx_avail <= 1;
							rx_error <= 0;
						end else begin                  //   bas stop bit
							rx_error <= 1;
						end
					end else begin
						rxd_reg <= { uart_rxd2, rxd_reg[7:1] };
					end
				end
			end 
		end
	end
end

//-----------------------------------------------------------------
// UART TX Logic
//-----------------------------------------------------------------
reg [3:0] tx_bitcount;
reg [3:0] tx_count16;
reg [7:0] txd_reg;

always @ (posedge clk)
begin
	if (reset) begin
		tx_busy     <= 0;
		uart_txd    <= 1;
		tx_count16  <= 0;
	end else begin
		if (tx_wr && !tx_busy) begin
			txd_reg     <= tx_data;
			tx_bitcount <= 0;
			tx_count16  <= 0;
			tx_busy     <= 1;
		end 

		if (enable16) begin
			tx_count16  <= tx_count16 + 1;

			if ((tx_count16 == 0) && tx_busy) begin
				tx_bitcount <= tx_bitcount + 1;
				
				if (tx_bitcount == 0) begin
					uart_txd <= 'b0;
				end else if (tx_bitcount ==  9) begin
					uart_txd <= 'b1;
				end else if (tx_bitcount == 10) begin
					tx_bitcount <= 0;
					tx_busy  <= 0;
				end else begin
					uart_txd <= txd_reg[0];
					txd_reg  <= { 1'b0, txd_reg[7:1] };
				end
			end

		end
	end
end


endmodule

FIFO.v
module FIFO
	#(
		parameter DATO_WIDTH = 8,
		parameter FIFO_LENGTH = 53
	)(
		input wclk,
		input [DATO_WIDTH-1:0] datin,
		input rclk,
		input rst,
		output reg [DATO_WIDTH-1:0] datout,
		output reg full,
		output reg empy,
		output reg dato
	);

// Registers	
	reg [DATO_WIDTH-1:0] f [0:(FIFO_LENGTH-1)];
	
	reg orwr;
	
	reg [5:0] cont = 0;
	reg [5:0] contw = 0;
	reg [5:0] contr = 0;
	
	always @(posedge orwr) begin

		if(rst) begin
			f[0] <= 3'b000;
			f[1] <= 3'b000;
			f[2] <= 3'b000;
			f[3] <= 3'b000;
			f[4] <= 3'b000;
			cont <= 0;
			contw <= 0;
			contr <= 0;
			datout <= 0;
		end else begin
			case({rclk,wclk})
				2'b01:
					if(~full) begin
						f[contw] <= datin;
						contw <= contw + 3'b001;	
						if(contw >= (FIFO_LENGTH - 1)) contw <= 3'b000;
						cont <= cont + 3'b001;
					end

				2'b10:
					if(~empy) begin
						datout <= f[contr];
						f[contr] <= 0;
						contr <= contr + 3'b001;
						if(contr >= (FIFO_LENGTH - 1)) contr <= 3'b000;
						cont <= cont - 3'b001;
					end

				2'b11:
					if(full) begin

						datout <= f[contr];
						f[contr] <= 0;
						contr <= contr + 3'b001;
						if(contr >= (FIFO_LENGTH - 1)) contr <= 3'b000;

						f[contw] <= datin;
						contw <= contw + 3'b001;	
						if(contw >= (FIFO_LENGTH - 1)) contw <= 3'b000;

					end else if(empy) begin
						
						datout <= datin;

					end else begin

						if(~full) begin
							f[contw] <= datin;
							contw <= contw + 3'b001;	
							if(contw >= (FIFO_LENGTH - 1)) contw <= 3'b000;
						end

						if(~empy) begin
							datout <= f[contr];
							f[contr] <= 0;
							contr <= contr + 3'b001;
							if(contr >= (FIFO_LENGTH - 1)) contr <= 3'b000;
						end
					end
			endcase
		end

	end
	
	always @(*) begin
		orwr = wclk | rclk | rst;
		if(cont == 0) begin
			empy = 1;
			dato = 0;
			full = 0;
		end
		if(cont > 0) begin
			empy = 0;
			dato = 1;
			full = 0;
		end
		if(cont == FIFO_LENGTH) begin
			empy = 0;
			dato = 0;
			full = 1;
		end
	end

endmodule

camera_fifo.v
module camera_fifo(clk, reset, tx, rx, datout, rclk, empy, dato, full);
	input rx;
	input reset;
	output tx;
	input clk;
	
	input rclk;
	output [7:0] datout;
	
	output full;
	output empy;
	output dato;
	
	wire wclk;
	reg [7:0] datin = 8'h00;
	reg rst = 0;

	wire [7:0] rx_data;
	reg [7:0] tx_data = 8'h00;
	reg tx_wr = 0;
	wire rx_avail;
	wire rx_busy;
	wire tx_busy;
	wire rx_error;
	
	FIFO #(
		.DATO_WIDTH(8),
		.FIFO_LENGTH(53)

	) fifo(
		.wclk(wclk),
		.datin(rx_data), 
		.rclk(rclk),
		.datout(datout), 
		.full(full), 
		.empy(empy), 
		.dato(dato), 
		.rst(reset)
	);
	
	
	uart peri(
		.reset(reset),
		.clk(clk),
		// UART lines
		.uart_rxd(rx),
		.uart_txd(tx),
		// 
		.rx_data(rx_data),
		.rx_avail(rx_avail),
		.rx_error(rx_error),
		.rx_busy(rx_busy),
		.tx_data(tx_data),
		.tx_wr(tx_wr),
		.tx_busy(tx_busy)
	);
	
	/*always @(negedge rx_busy) begin
		if(rx_avail == 1) begin
			datin <= rx_data;
			wr <= 1;
			wclk <= 1;
		end
	end
	
	always @(posedge rx_busy) begin
		wclk <= 0;
		wr <= 0;
	end*/

	reg w = 0;
	assign wclk = ~rx_busy & w;

	always @(posedge clk) begin
		if(~rx_busy) begin
			w <= 0;
		end else begin
			w <= 1;
		end
	end
/*
	always @(posedge clk) begin
		if (rx_avail && ~rx_error && ~rx_busy) begin
			tx_data <= rx_data;

		end
	end
		*/	
	
endmodule

camera_fifo_TB.v
module camera_fifo_TB; 
reg reset;
reg clk;
reg [7:0] Tx;  //Dato de envio
reg send;
reg rdx;
wire txd;
reg rclk = 0;

camera_fifo  uut(
.clk(clk),
.reset(reset),
.rx(rdx),
.tx(txd),
.rclk(rclk)
);

reg [5:0] cont = 0;
	
initial begin 
	clk <= 0;
	rdx <= 1;
	reset=1;
	#10; reset=0;
	
end
	
always #1 clk <= ~clk;

always begin
	for(cont = 0; cont < 15; cont = cont + 1) begin
		#2700;
		rdx <= ~rdx;
	end
	rclk <= 1;
	#2;
	rclk <= 0;
	#2;
	rclk <= 1;
	#2;
	rclk <= 0;
	#2;
end
	 

initial begin//: TEST_CASE
  $dumpfile("camera_fifo_TB.vcd");
  $dumpvars(-1, uut);
  #80000 $finish;



end

endmodule

simulation/camera_fifo_TB.vcd
$date
	Fri Mar 16 18:51:53 2018
$end
$version
	Icarus Verilog
$end
$timescale
	1s
$end
$scope module camera_fifo_TB $end
$scope module uut $end
$var wire 1 ! clk $end
$var wire 1 " dato $end
$var wire 8 # datout [7:0] $end
$var wire 1 $ empy $end
$var wire 1 % full $end
$var wire 1 & rclk $end
$var wire 1 ' reset $end
$var wire 1 ( rx $end
$var wire 1 ) rx_avail $end
$var wire 1 * rx_busy $end
$var wire 8 + rx_data [7:0] $end
$var wire 1 , rx_error $end
$var wire 1 - tx $end
$var wire 1 . tx_busy $end
$var wire 1 / wclk $end
$var reg 8 0 datin [7:0] $end
$var reg 1 1 rst $end
$var reg 8 2 tx_data [7:0] $end
$var reg 1 3 tx_wr $end
$var reg 1 4 w $end
$scope module fifo $end
$var wire 8 5 datin [7:0] $end
$var wire 1 & rclk $end
$var wire 1 ' rst $end
$var wire 1 / wclk $end
$var reg 6 6 cont [5:0] $end
$var reg 6 7 contr [5:0] $end
$var reg 6 8 contw [5:0] $end
$var reg 1 9 dato $end
$var reg 8 : datout [7:0] $end
$var reg 1 ; empy $end
$var reg 1 < full $end
$var reg 1 = orwr $end
$upscope $end
$scope module peri $end
$var wire 1 ! clk $end
$var wire 1 > enable16 $end
$var wire 1 ' reset $end
$var wire 1 ? rx_ack $end
$var wire 8 @ tx_data [7:0] $end
$var wire 1 A tx_wr $end
$var wire 1 ( uart_rxd $end
$var reg 16 B enable16_counter [15:0] $end
$var reg 1 C rx_avail $end
$var reg 4 D rx_bitcount [3:0] $end
$var reg 1 E rx_busy $end
$var reg 4 F rx_count16 [3:0] $end
$var reg 8 G rx_data [7:0] $end
$var reg 1 H rx_error $end
$var reg 8 I rxd_reg [7:0] $end
$var reg 4 J tx_bitcount [3:0] $end
$var reg 1 K tx_busy $end
$var reg 4 L tx_count16 [3:0] $end
$var reg 8 M txd_reg [7:0] $end
$var reg 1 N uart_rxd1 $end
$var reg 1 O uart_rxd2 $end
$var reg 1 P uart_txd $end
$upscope $end
$upscope $end
$upscope $end
$enddefinitions $end
#0
$dumpvars
xP
xO
xN
bx M
bx L
xK
bx J
bx I
xH
bx G
bx F
xE
bx D
xC
bx B
0A
b0 @
z?
x>
1=
0<
1;
b0 :
09
b0 8
b0 7
b0 6
b0 5
04
03
b0 2
01
b0 0
0/
x.
x-
x,
bx +
x*
x)
1(
1'
0&
0%
1$
b0 #
0"
0!
$end
#1
1/
b1010000 B
0>
1N
0H
0,
0C
0)
b0 D
b0 F
0E
0*
b0 L
1P
1-
0K
0.
14
1!
#2
0!
#3
0/
04
1O
1!
#4
0!
#5
1!
#6
0!
#7
1!
#8
0!
#9
1!
#10
0!
0=
0'
#11
b1001111 B
1!
#12
0!
#13
b1001110 B
1!
#14
0!
#15
b1001101 B
1!
#16
0!
#17
b1001100 B
1!
#18
0!
#19
b1001011 B
1!
#20
0!
#21
b1001010 B
1!
#22
0!
#23
b1001001 B
1!
#24
0!
#25
b1001000 B
1!
#26
0!
#27
b1000111 B
1!
#28
0!
#29
b1000110 B
1!
#30
0!
#31
b1000101 B
1!
#32
0!
#33
b1000100 B
1!
#34
0!
#35
b1000011 B
1!
#36
0!
#37
b1000010 B
1!
#38
0!
#39
b1000001 B
1!
#40
0!
#41
b1000000 B
1!
#42
0!
#43
b111111 B
1!
#44
0!
#45
b111110 B
1!
#46
0!
#47
b111101 B
1!
#48
0!
#49
b111100 B
1!
#50
0!
#51
b111011 B
1!
#52
0!
#53
b111010 B
1!
#54
0!
#55
b111001 B
1!
#56
0!
#57
b111000 B
1!
#58
0!
#59
b110111 B
1!
#60
0!
#61
b110110 B
1!
#62
0!
#63
b110101 B
1!
#64
0!
#65
b110100 B
1!
#66
0!
#67
b110011 B
1!
#68
0!
#69
b110010 B
1!
#70
0!
#71
b110001 B
1!
#72
0!
#73
b110000 B
1!
#74
0!
#75
b101111 B
1!
#76
0!
#77
b101110 B
1!
#78
0!
#79
b101101 B
1!
#80
0!
#81
b101100 B
1!
#82
0!
#83
b101011 B
1!
#84
0!
#85
b101010 B
1!
#86
0!
#87
b101001 B
1!
#88
0!
#89
b101000 B
1!
#90
0!
#91
b100111 B
1!
#92
0!
#93
b100110 B
1!
#94
0!
#95
b100101 B
1!
#96
0!
#97
b100100 B
1!
#98
0!
#99
b100011 B
1!
#100
0!
#101
b100010 B
1!
#102
0!
#103
b100001 B
1!
#104
0!
#105
b100000 B
1!
#106
0!
#107
b11111 B
1!
#108
0!
#109
b11110 B
1!
#110
0!
#111
b11101 B
1!
#112
0!
#113
b11100 B
1!
#114
0!
#115
b11011 B
1!
#116
0!
#117
b11010 B
1!
#118
0!
#119
b11001 B
1!
#120
0!
#121
b11000 B
1!
#122
0!
#123
b10111 B
1!
#124
0!
#125
b10110 B
1!
#126
0!
#127
b10101 B
1!
#128
0!
#129
b10100 B
1!
#130
0!
#131
b10011 B
1!
#132
0!
#133
b10010 B
1!
#134
0!
#135
b10001 B
1!
#136
0!
#137
b10000 B
1!
#138
0!
#139
b1111 B
1!
#140
0!
#141
b1110 B
1!
#142
0!
#143
b1101 B
1!
#144
0!
#145
b1100 B
1!
#146
0!
#147
b1011 B
1!
#148
0!
#149
b1010 B
1!
#150
0!
#151
b1001 B
1!
#152
0!
#153
b1000 B
1!
#154
0!
#155
b111 B
1!
#156
0!
#157
b110 B
1!
#158
0!
#159
b101 B
1!
#160
0!
#161
b100 B
1!
#162
0!
#163
b11 B
1!
#164
0!
#165
b10 B
1!
#166
0!
#167
b1 B
1!
#168
0!
#169
b0 B
1>
1!
#170
0!
#171
b1 L
b1010000 B
0>
1!
#172
0!
#173
b1001111 B
1!
#174
0!
#175
b1001110 B
1!
#176
0!
#177
b1001101 B
1!
#178
0!
#179
b1001100 B
1!
#180
0!
#181
b1001011 B
1!
#182
0!
#183
b1001010 B
1!
#184
0!
#185
b1001001 B
1!
#186
0!
#187
b1001000 B
1!
#188
0!
#189
b1000111 B
1!
#190
0!
#191
b1000110 B
1!
#192
0!
#193
b1000101 B
1!
#194
0!
#195
b1000100 B
1!
#196
0!
#197
b1000011 B
1!
#198
0!
#199
b1000010 B
1!
#200
0!
#201
b1000001 B
1!
#202
0!
#203
b1000000 B
1!
#204
0!
#205
b111111 B
1!
#206
0!
#207
b111110 B
1!
#208
0!
#209
b111101 B
1!
#210
0!
#211
b111100 B
1!
#212
0!
#213
b111011 B
1!
#214
0!
#215
b111010 B
1!
#216
0!
#217
b111001 B
1!
#218
0!
#219
b111000 B
1!
#220
0!
#221
b110111 B
1!
#222
0!
#223
b110110 B
1!
#224
0!
#225
b110101 B
1!
#226
0!
#227
b110100 B
1!
#228
0!
#229
b110011 B
1!
#230
0!
#231
b110010 B
1!
#232
0!
#233
b110001 B
1!
#234
0!
#235
b110000 B
1!
#236
0!
#237
b101111 B
1!
#238
0!
#239
b101110 B
1!
#240
0!
#241
b101101 B
1!
#242
0!
#243
b101100 B
1!
#244
0!
#245
b101011 B
1!
#246
0!
#247
b101010 B
1!
#248
0!
#249
b101001 B
1!
#250
0!
#251
b101000 B
1!
#252
0!
#253
b100111 B
1!
#254
0!
#255
b100110 B
1!
#256
0!
#257
b100101 B
1!
#258
0!
#259
b100100 B
1!
#260
0!
#261
b100011 B
1!
#262
0!
#263
b100010 B
1!
#264
0!
#265
b100001 B
1!
#266
0!
#267
b100000 B
1!
#268
0!
#269
b11111 B
1!
#270
0!
#271
b11110 B
1!
#272
0!
#273
b11101 B
1!
#274
0!
#275
b11100 B
1!
#276
0!
#277
b11011 B
1!
#278
0!
#279
b11010 B
1!
#280
0!
#281
b11001 B
1!
#282
0!
#283
b11000 B
1!
#284
0!
#285
b10111 B
1!
#286
0!
#287
b10110 B
1!
#288
0!
#289
b10101 B
1!
#290
0!
#291
b10100 B
1!
#292
0!
#293
b10011 B
1!
#294
0!
#295
b10010 B
1!
#296
0!
#297
b10001 B
1!
#298
0!
#299
b10000 B
1!
#300
0!
#301
b1111 B
1!
#302
0!
#303
b1110 B
1!
#304
0!
#305
b1101 B
1!
#306
0!
#307
b1100 B
1!
#308
0!
#309
b1011 B
1!
#310
0!
#311
b1010 B
1!
#312
0!
#313
b1001 B
1!
#314
0!
#315
b1000 B
1!
#316
0!
#317
b111 B
1!
#318
0!
#319
b110 B
1!
#320
0!
#321
b101 B
1!
#322
0!
#323
b100 B
1!
#324
0!
#325
b11 B
1!
#326
0!
#327
b10 B
1!
#328
0!
#329
b1 B
1!
#330
0!
#331
b0 B
1>
1!
#332
0!
#333
b1010000 B
0>
b10 L
1!
#334
0!
#335
b1001111 B
1!
#336
0!
#337
b1001110 B
1!
#338
0!
#339
b1001101 B
1!
#340
0!
#341
b1001100 B
1!
#342
0!
#343
b1001011 B
1!
#344
0!
#345
b1001010 B
1!
#346
0!
#347
b1001001 B
1!
#348
0!
#349
b1001000 B
1!
#350
0!
#351
b1000111 B
1!
#352
0!
#353
b1000110 B
1!
#354
0!
#355
b1000101 B
1!
#356
0!
#357
b1000100 B
1!
#358
0!
#359
b1000011 B
1!
#360
0!
#361
b1000010 B
1!
#362
0!
#363
b1000001 B
1!
#364
0!
#365
b1000000 B
1!
#366
0!
#367
b111111 B
1!
#368
0!
#369
b111110 B
1!
#370
0!
#371
b111101 B
1!
#372
0!
#373
b111100 B
1!
#374
0!
#375
b111011 B
1!
#376
0!
#377
b111010 B
1!
#378
0!
#379
b111001 B
1!
#380
0!
#381
b111000 B
1!
#382
0!
#383
b110111 B
1!
#384
0!
#385
b110110 B
1!
#386
0!
#387
b110101 B
1!
#388
0!
#389
b110100 B
1!
#390
0!
#391
b110011 B
1!
#392
0!
#393
b110010 B
1!
#394
0!
#395
b110001 B
1!
#396
0!
#397
b110000 B
1!
#398
0!
#399
b101111 B
1!
#400
0!
#401
b101110 B
1!
#402
0!
#403
b101101 B
1!
#404
0!
#405
b101100 B
1!
#406
0!
#407
b101011 B
1!
#408
0!
#409
b101010 B
1!
#410
0!
#411
b101001 B
1!
#412
0!
#413
b101000 B
1!
#414
0!
#415
b100111 B
1!
#416
0!
#417
b100110 B
1!
#418
0!
#419
b100101 B
1!
#420
0!
#421
b100100 B
1!
#422
0!
#423
b100011 B
1!
#424
0!
#425
b100010 B
1!
#426
0!
#427
b100001 B
1!
#428
0!
#429
b100000 B
1!
#430
0!
#431
b11111 B
1!
#432
0!
#433
b11110 B
1!
#434
0!
#435
b11101 B
1!
#436
0!
#437
b11100 B
1!
#438
0!
#439
b11011 B
1!
#440
0!
#441
b11010 B
1!
#442
0!
#443
b11001 B
1!
#444
0!
#445
b11000 B
1!
#446
0!
#447
b10111 B
1!
#448
0!
#449
b10110 B
1!
#450
0!
#451
b10101 B
1!
#452
0!
#453
b10100 B
1!
#454
0!
#455
b10011 B
1!
#456
0!
#457
b10010 B
1!
#458
0!
#459
b10001 B
1!
#460
0!
#461
b10000 B
1!
#462
0!
#463
b1111 B
1!
#464
0!
#465
b1110 B
1!
#466
0!
#467
b1101 B
1!
#468
0!
#469
b1100 B
1!
#470
0!
#471
b1011 B
1!
#472
0!
#473
b1010 B
1!
#474
0!
#475
b1001 B
1!
#476
0!
#477
b1000 B
1!
#478
0!
#479
b111 B
1!
#480
0!
#481
b110 B
1!
#482
0!
#483
b101 B
1!
#484
0!
#485
b100 B
1!
#486
0!
#487
b11 B
1!
#488
0!
#489
b10 B
1!
#490
0!
#491
b1 B
1!
#492
0!
#493
b0 B
1>
1!
#494
0!
#495
b11 L
b1010000 B
0>
1!
#496
0!
#497
b1001111 B
1!
#498
0!
#499
b1001110 B
1!
#500
0!
#501
b1001101 B
1!
#502
0!
#503
b1001100 B
1!
#504
0!
#505
b1001011 B
1!
#506
0!
#507
b1001010 B
1!
#508
0!
#509
b1001001 B
1!
#510
0!
#511
b1001000 B
1!
#512
0!
#513
b1000111 B
1!
#514
0!
#515
b1000110 B
1!
#516
0!
#517
b1000101 B
1!
#518
0!
#519
b1000100 B
1!
#520
0!
#521
b1000011 B
1!
#522
0!
#523
b1000010 B
1!
#524
0!
#525
b1000001 B
1!
#526
0!
#527
b1000000 B
1!
#528
0!
#529
b111111 B
1!
#530
0!
#531
b111110 B
1!
#532
0!
#533
b111101 B
1!
#534
0!
#535
b111100 B
1!
#536
0!
#537
b111011 B
1!
#538
0!
#539
b111010 B
1!
#540
0!
#541
b111001 B
1!
#542
0!
#543
b111000 B
1!
#544
0!
#545
b110111 B
1!
#546
0!
#547
b110110 B
1!
#548
0!
#549
b110101 B
1!
#550
0!
#551
b110100 B
1!
#552
0!
#553
b110011 B
1!
#554
0!
#555
b110010 B
1!
#556
0!
#557
b110001 B
1!
#558
0!
#559
b110000 B
1!
#560
0!
#561
b101111 B
1!
#562
0!
#563
b101110 B
1!
#564
0!
#565
b101101 B
1!
#566
0!
#567
b101100 B
1!
#568
0!
#569
b101011 B
1!
#570
0!
#571
b101010 B
1!
#572
0!
#573
b101001 B
1!
#574
0!
#575
b101000 B
1!
#576
0!
#577
b100111 B
1!
#578
0!
#579
b100110 B
1!
#580
0!
#581
b100101 B
1!
#582
0!
#583
b100100 B
1!
#584
0!
#585
b100011 B
1!
#586
0!
#587
b100010 B
1!
#588
0!
#589
b100001 B
1!
#590
0!
#591
b100000 B
1!
#592
0!
#593
b11111 B
1!
#594
0!
#595
b11110 B
1!
#596
0!
#597
b11101 B
1!
#598
0!
#599
b11100 B
1!
#600
0!
#601
b11011 B
1!
#602
0!
#603
b11010 B
1!
#604
0!
#605
b11001 B
1!
#606
0!
#607
b11000 B
1!
#608
0!
#609
b10111 B
1!
#610
0!
#611
b10110 B
1!
#612
0!
#613
b10101 B
1!
#614
0!
#615
b10100 B
1!
#616
0!
#617
b10011 B
1!
#618
0!
#619
b10010 B
1!
#620
0!
#621
b10001 B
1!
#622
0!
#623
b10000 B
1!
#624
0!
#625
b1111 B
1!
#626
0!
#627
b1110 B
1!
#628
0!
#629
b1101 B
1!
#630
0!
#631
b1100 B
1!
#632
0!
#633
b1011 B
1!
#634
0!
#635
b1010 B
1!
#636
0!
#637
b1001 B
1!
#638
0!
#639
b1000 B
1!
#640
0!
#641
b111 B
1!
#642
0!
#643
b110 B
1!
#644
0!
#645
b101 B
1!
#646
0!
#647
b100 B
1!
#648
0!
#649
b11 B
1!
#650
0!
#651
b10 B
1!
#652
0!
#653
b1 B
1!
#654
0!
#655
b0 B
1>
1!
#656
0!
#657
b1010000 B
0>
b100 L
1!
#658
0!
#659
b1001111 B
1!
#660
0!
#661
b1001110 B
1!
#662
0!
#663
b1001101 B
1!
#664
0!
#665
b1001100 B
1!
#666
0!
#667
b1001011 B
1!
#668
0!
#669
b1001010 B
1!
#670
0!
#671
b1001001 B
1!
#672
0!
#673
b1001000 B
1!
#674
0!
#675
b1000111 B
1!
#676
0!
#677
b1000110 B
1!
#678
0!
#679
b1000101 B
1!
#680
0!
#681
b1000100 B
1!
#682
0!
#683
b1000011 B
1!
#684
0!
#685
b1000010 B
1!
#686
0!
#687
b1000001 B
1!
#688
0!
#689
b1000000 B
1!
#690
0!
#691
b111111 B
1!
#692
0!
#693
b111110 B
1!
#694
0!
#695
b111101 B
1!
#696
0!
#697
b111100 B
1!
#698
0!
#699
b111011 B
1!
#700
0!
#701
b111010 B
1!
#702
0!
#703
b111001 B
1!
#704
0!
#705
b111000 B
1!
#706
0!
#707
b110111 B
1!
#708
0!
#709
b110110 B
1!
#710
0!
#711
b110101 B
1!
#712
0!
#713
b110100 B
1!
#714
0!
#715
b110011 B
1!
#716
0!
#717
b110010 B
1!
#718
0!
#719
b110001 B
1!
#720
0!
#721
b110000 B
1!
#722
0!
#723
b101111 B
1!
#724
0!
#725
b101110 B
1!
#726
0!
#727
b101101 B
1!
#728
0!
#729
b101100 B
1!
#730
0!
#731
b101011 B
1!
#732
0!
#733
b101010 B
1!
#734
0!
#735
b101001 B
1!
#736
0!
#737
b101000 B
1!
#738
0!
#739
b100111 B
1!
#740
0!
#741
b100110 B
1!
#742
0!
#743
b100101 B
1!
#744
0!
#745
b100100 B
1!
#746
0!
#747
b100011 B
1!
#748
0!
#749
b100010 B
1!
#750
0!
#751
b100001 B
1!
#752
0!
#753
b100000 B
1!
#754
0!
#755
b11111 B
1!
#756
0!
#757
b11110 B
1!
#758
0!
#759
b11101 B
1!
#760
0!
#761
b11100 B
1!
#762
0!
#763
b11011 B
1!
#764
0!
#765
b11010 B
1!
#766
0!
#767
b11001 B
1!
#768
0!
#769
b11000 B
1!
#770
0!
#771
b10111 B
1!
#772
0!
#773
b10110 B
1!
#774
0!
#775
b10101 B
1!
#776
0!
#777
b10100 B
1!
#778
0!
#779
b10011 B
1!
#780
0!
#781
b10010 B
1!
#782
0!
#783
b10001 B
1!
#784
0!
#785
b10000 B
1!
#786
0!
#787
b1111 B
1!
#788
0!
#789
b1110 B
1!
#790
0!
#791
b1101 B
1!
#792
0!
#793
b1100 B
1!
#794
0!
#795
b1011 B
1!
#796
0!
#797
b1010 B
1!
#798
0!
#799
b1001 B
1!
#800
0!
#801
b1000 B
1!
#802
0!
#803
b111 B
1!
#804
0!
#805
b110 B
1!
#806
0!
#807
b101 B
1!
#808
0!
#809
b100 B
1!
#810
0!
#811
b11 B
1!
#812
0!
#813
b10 B
1!
#814
0!
#815
b1 B
1!
#816
0!
#817
b0 B
1>
1!
#818
0!
#819
b101 L
b1010000 B
0>
1!
#820
0!
#821
b1001111 B
1!
#822
0!
#823
b1001110 B
1!
#824
0!
#825
b1001101 B
1!
#826
0!
#827
b1001100 B
1!
#828
0!
#829
b1001011 B
1!
#830
0!
#831
b1001010 B
1!
#832
0!
#833
b1001001 B
1!
#834
0!
#835
b1001000 B
1!
#836
0!
#837
b1000111 B
1!
#838
0!
#839
b1000110 B
1!
#840
0!
#841
b1000101 B
1!
#842
0!
#843
b1000100 B
1!
#844
0!
#845
b1000011 B
1!
#846
0!
#847
b1000010 B
1!
#848
0!
#849
b1000001 B
1!
#850
0!
#851
b1000000 B
1!
#852
0!
#853
b111111 B
1!
#854
0!
#855
b111110 B
1!
#856
0!
#857
b111101 B
1!
#858
0!
#859
b111100 B
1!
#860
0!
#861
b111011 B
1!
#862
0!
#863
b111010 B
1!
#864
0!
#865
b111001 B
1!
#866
0!
#867
b111000 B
1!
#868
0!
#869
b110111 B
1!
#870
0!
#871
b110110 B
1!
#872
0!
#873
b110101 B
1!
#874
0!
#875
b110100 B
1!
#876
0!
#877
b110011 B
1!
#878
0!
#879
b110010 B
1!
#880
0!
#881
b110001 B
1!
#882
0!
#883
b110000 B
1!
#884
0!
#885
b101111 B
1!
#886
0!
#887
b101110 B
1!
#888
0!
#889
b101101 B
1!
#890
0!
#891
b101100 B
1!
#892
0!
#893
b101011 B
1!
#894
0!
#895
b101010 B
1!
#896
0!
#897
b101001 B
1!
#898
0!
#899
b101000 B
1!
#900
0!
#901
b100111 B
1!
#902
0!
#903
b100110 B
1!
#904
0!
#905
b100101 B
1!
#906
0!
#907
b100100 B
1!
#908
0!
#909
b100011 B
1!
#910
0!
#911
b100010 B
1!
#912
0!
#913
b100001 B
1!
#914
0!
#915
b100000 B
1!
#916
0!
#917
b11111 B
1!
#918
0!
#919
b11110 B
1!
#920
0!
#921
b11101 B
1!
#922
0!
#923
b11100 B
1!
#924
0!
#925
b11011 B
1!
#926
0!
#927
b11010 B
1!
#928
0!
#929
b11001 B
1!
#930
0!
#931
b11000 B
1!
#932
0!
#933
b10111 B
1!
#934
0!
#935
b10110 B
1!
#936
0!
#937
b10101 B
1!
#938
0!
#939
b10100 B
1!
#940
0!
#941
b10011 B
1!
#942
0!
#943
b10010 B
1!
#944
0!
#945
b10001 B
1!
#946
0!
#947
b10000 B
1!
#948
0!
#949
b1111 B
1!
#950
0!
#951
b1110 B
1!
#952
0!
#953
b1101 B
1!
#954
0!
#955
b1100 B
1!
#956
0!
#957
b1011 B
1!
#958
0!
#959
b1010 B
1!
#960
0!
#961
b1001 B
1!
#962
0!
#963
b1000 B
1!
#964
0!
#965
b111 B
1!
#966
0!
#967
b110 B
1!
#968
0!
#969
b101 B
1!
#970
0!
#971
b100 B
1!
#972
0!
#973
b11 B
1!
#974
0!
#975
b10 B
1!
#976
0!
#977
b1 B
1!
#978
0!
#979
b0 B
1>
1!
#980
0!
#981
b1010000 B
0>
b110 L
1!
#982
0!
#983
b1001111 B
1!
#984
0!
#985
b1001110 B
1!
#986
0!
#987
b1001101 B
1!
#988
0!
#989
b1001100 B
1!
#990
0!
#991
b1001011 B
1!
#992
0!
#993
b1001010 B
1!
#994
0!
#995
b1001001 B
1!
#996
0!
#997
b1001000 B
1!
#998
0!
#999
b1000111 B
1!
#1000
0!
#1001
b1000110 B
1!
#1002
0!
#1003
b1000101 B
1!
#1004
0!
#1005
b1000100 B
1!
#1006
0!
#1007
b1000011 B
1!
#1008
0!
#1009
b1000010 B
1!
#1010
0!
#1011
b1000001 B
1!
#1012
0!
#1013
b1000000 B
1!
#1014
0!
#1015
b111111 B
1!
#1016
0!
#1017
b111110 B
1!
#1018
0!
#1019
b111101 B
1!
#1020
0!
#1021
b111100 B
1!
#1022
0!
#1023
b111011 B
1!
#1024
0!
#1025
b111010 B
1!
#1026
0!
#1027
b111001 B
1!
#1028
0!
#1029
b111000 B
1!
#1030
0!
#1031
b110111 B
1!
#1032
0!
#1033
b110110 B
1!
#1034
0!
#1035
b110101 B
1!
#1036
0!
#1037
b110100 B
1!
#1038
0!
#1039
b110011 B
1!
#1040
0!
#1041
b110010 B
1!
#1042
0!
#1043
b110001 B
1!
#1044
0!
#1045
b110000 B
1!
#1046
0!
#1047
b101111 B
1!
#1048
0!
#1049
b101110 B
1!
#1050
0!
#1051
b101101 B
1!
#1052
0!
#1053
b101100 B
1!
#1054
0!
#1055
b101011 B
1!
#1056
0!
#1057
b101010 B
1!
#1058
0!
#1059
b101001 B
1!
#1060
0!
